{
  "pdf_page_number": 7,
  "footer_page_number": 172,
  "table_number": 1,
  "family_id": 89,
  "extraction_method": "vlm",
  "product_count": 23,
  "products": [
    {
      "family_id": 89,
      "product_code": "4201-02-03-1",
      "specifications": "{\"Artikelnr.\": \"4201-02-03-1\", \"Gänga\": \"G 1/8\\\"\", \"Typ\": \"IR\", \"Slang ID\": \"3/16\\\"\"}",
      "configuration_type": "STANDARD",
      "page_number": null
    },
    {
      "family_id": 89,
      "product_code": "4201-02-04-1",
      "specifications": "{\"Artikelnr.\": \"4201-02-04-1\", \"Gänga\": \"G 1/8\\\"\", \"Typ\": \"IR\", \"Slang ID\": \"1/4\\\"\"}",
      "configuration_type": "STANDARD",
      "page_number": null
    },
    {
      "family_id": 89,
      "product_code": "4201-04-03-1",
      "specifications": "{\"Artikelnr.\": \"4201-04-03-1\", \"Gänga\": \"G 1/4\\\"\", \"Typ\": \"IR\", \"Slang ID\": \"3/16\\\"\"}",
      "configuration_type": "STANDARD",
      "page_number": null
    },
    {
      "family_id": 89,
      "product_code": "4201-04-04-1",
      "specifications": "{\"Artikelnr.\": \"4201-04-04-1\", \"Gänga\": \"G 1/4\\\"\", \"Typ\": \"IR\", \"Slang ID\": \"1/4\\\"\"}",
      "configuration_type": "STANDARD",
      "page_number": null
    },
    {
      "family_id": 89,
      "product_code": "4201-04-05-1",
      "specifications": "{\"Artikelnr.\": \"4201-04-05-1\", \"Gänga\": \"G 1/4\\\"\", \"Typ\": \"IR\", \"Slang ID\": \"5/16\\\"\"}",
      "configuration_type": "STANDARD",
      "page_number": null
    },
    {
      "family_id": 89,
      "product_code": "4201-04-06-1",
      "specifications": "{\"Artikelnr.\": \"4201-04-06-1\", \"Gänga\": \"G 1/4\\\"\", \"Typ\": \"IR\", \"Slang ID\": \"3/8\\\"\"}",
      "configuration_type": "STANDARD",
      "page_number": null
    },
    {
      "family_id": 89,
      "product_code": "4201-06-04-1",
      "specifications": "{\"Artikelnr.\": \"4201-06-04-1\", \"Gänga\": \"G 3/8\\\"\", \"Typ\": \"IR\", \"Slang ID\": \"1/4\\\"\"}",
      "configuration_type": "STANDARD",
      "page_number": null
    },
    {
      "family_id": 89,
      "product_code": "4201-06-05-1",
      "specifications": "{\"Artikelnr.\": \"4201-06-05-1\", \"Gänga\": \"G 3/8\\\"\", \"Typ\": \"IR\", \"Slang ID\": \"5/16\\\"\"}",
      "configuration_type": "STANDARD",
      "page_number": null
    },
    {
      "family_id": 89,
      "product_code": "4201-06-06-1",
      "specifications": "{\"Artikelnr.\": \"4201-06-06-1\", \"Gänga\": \"G 3/8\\\"\", \"Typ\": \"IR\", \"Slang ID\": \"3/8\\\"\"}",
      "configuration_type": "STANDARD",
      "page_number": null
    },
    {
      "family_id": 89,
      "product_code": "4201-06-08-1",
      "specifications": "{\"Artikelnr.\": \"4201-06-08-1\", \"Gänga\": \"G 3/8\\\"\", \"Typ\": \"IR\", \"Slang ID\": \"1/2\\\"\"}",
      "configuration_type": "STANDARD",
      "page_number": null
    },
    {
      "family_id": 89,
      "product_code": "4201-08-06-1",
      "specifications": "{\"Artikelnr.\": \"4201-08-06-1\", \"Gänga\": \"G 1/2\\\"\", \"Typ\": \"IR\", \"Slang ID\": \"3/8\\\"\"}",
      "configuration_type": "STANDARD",
      "page_number": null
    },
    {
      "family_id": 89,
      "product_code": "4201-08-06-15",
      "specifications": "{\"Artikelnr.\": \"4201-08-06-15\", \"Gänga\": \"G 1/2\\\"\", \"Typ\": \"IR\", \"Slang ID\": \"3/8\\\"\", \"Nyckelvidd\": \"25 mm\"}",
      "configuration_type": "STANDARD",
      "page_number": null
    },
    {
      "family_id": 89,
      "product_code": "4201-08-08-1",
      "specifications": "{\"Artikelnr.\": \"4201-08-08-1\", \"Gänga\": \"G 1/2\\\"\", \"Typ\": \"IR\", \"Slang ID\": \"1/2\\\"\"}",
      "configuration_type": "STANDARD",
      "page_number": null
    },
    {
      "family_id": 89,
      "product_code": "4201-08-08-15",
      "specifications": "{\"Artikelnr.\": \"4201-08-08-15\", \"Gänga\": \"G 1/2\\\"\", \"Typ\": \"IR\", \"Slang ID\": \"1/2\\\"\", \"Nyckelvidd\": \"25 mm\"}",
      "configuration_type": "STANDARD",
      "page_number": null
    },
    {
      "family_id": 89,
      "product_code": "4201-08-10-1",
      "specifications": "{\"Artikelnr.\": \"4201-08-10-1\", \"Gänga\": \"G 1/2\\\"\", \"Typ\": \"IR\", \"Slang ID\": \"5/8\\\"\"}",
      "configuration_type": "STANDARD",
      "page_number": null
    },
    {
      "family_id": 89,
      "product_code": "4201-08-12-1",
      "specifications": "{\"Artikelnr.\": \"4201-08-12-1\", \"Gänga\": \"G 1/2\\\"\", \"Typ\": \"IR\", \"Slang ID\": \"3/4\\\"\"}",
      "configuration_type": "STANDARD",
      "page_number": null
    },
    {
      "family_id": 89,
      "product_code": "4201-10-08-1",
      "specifications": "{\"Artikelnr.\": \"4201-10-08-1\", \"Gänga\": \"G 5/8\\\"\", \"Typ\": \"IR\", \"Slang ID\": \"1/2\\\"\"}",
      "configuration_type": "STANDARD",
      "page_number": null
    },
    {
      "family_id": 89,
      "product_code": "4201-10-10-1",
      "specifications": "{\"Artikelnr.\": \"4201-10-10-1\", \"Gänga\": \"G 5/8\\\"\", \"Typ\": \"IR\", \"Slang ID\": \"5/8\\\"\"}",
      "configuration_type": "STANDARD",
      "page_number": null
    },
    {
      "family_id": 89,
      "product_code": "4201-12-08-1",
      "specifications": "{\"Artikelnr.\": \"4201-12-08-1\", \"Gänga\": \"G 3/4\\\"\", \"Typ\": \"IR\", \"Slang ID\": \"1/2\\\"\"}",
      "configuration_type": "STANDARD",
      "page_number": null
    },
    {
      "family_id": 89,
      "product_code": "4201-12-10-1",
      "specifications": "{\"Artikelnr.\": \"4201-12-10-1\", \"Gänga\": \"G 3/4\\\"\", \"Typ\": \"IR\", \"Slang ID\": \"5/8\\\"\"}",
      "configuration_type": "STANDARD",
      "page_number": null
    },
    {
      "family_id": 89,
      "product_code": "4201-12-12-1",
      "specifications": "{\"Artikelnr.\": \"4201-12-12-1\", \"Gänga\": \"G 3/4\\\"\", \"Typ\": \"IR\", \"Slang ID\": \"3/4\\\"\"}",
      "configuration_type": "STANDARD",
      "page_number": null
    },
    {
      "family_id": 89,
      "product_code": "4201-16-12-1",
      "specifications": "{\"Artikelnr.\": \"4201-16-12-1\", \"Gänga\": \"G 1\\\"\", \"Typ\": \"IR\", \"Slang ID\": \"3/4\\\"\"}",
      "configuration_type": "STANDARD",
      "page_number": null
    },
    {
      "family_id": 89,
      "product_code": "4201-16-16-1",
      "specifications": "{\"Artikelnr.\": \"4201-16-16-1\", \"Gänga\": \"G 1\\\"\", \"Typ\": \"IR\", \"Slang ID\": \"1\\\"\"}",
      "configuration_type": "STANDARD",
      "page_number": null
    }
  ]
}